krb5ticket/__init__.py
krb5ticket/errors.py
krb5ticket/krb5.py
krb5ticket/ktutil.py
krb5ticket/ktutil_helpers.py
krb5ticket/version.py
python_krb5ticket-1.0.3.dist-info/LICENSE
python_krb5ticket-1.0.3.dist-info/METADATA
python_krb5ticket-1.0.3.dist-info/WHEEL
python_krb5ticket-1.0.3.dist-info/top_level.txt
python_krb5ticket-1.0.3.dist-info/RECORD
