Metadata-Version: 2.1
Name: python-krb5ticket
Version: 1.0.3
Summary: Simple Python wrapper to create Kerberos ticket-granting tickets (TGT)
Home-page: https://github.com/degagne/python-krb5ticket
Author: Deric Degagne
Author-email: deric.degagne@gmail.com
License: MIT
Platform: UNKNOWN
Classifier: Intended Audience :: Developers
Classifier: Intended Audience :: System Administrators
Classifier: Programming Language :: Python :: 3.6
Classifier: License :: OSI Approved :: MIT License
Requires-Python: >=3.6
License-File: LICENSE
Requires-Dist: gssapi
Requires-Dist: pandas (==1.1.3)
